{
  "expectedClusterCount": 3,
  "expectedDisplayText": "B#+",
  "expectedTopGlyphs": [
    "B",
    "#",
    "+"
  ],
  "name": "BSharpAugmentedCaptured01",
  "strokes": [
    {
      "bounds": {
        "maxX": 118.5,
        "maxY": 191,
        "minX": 117,
        "minY": 168.5
      },
      "points": [
        {
          "timeOffset": 0,
          "x": 118.5,
          "y": 168.5
        },
        {
          "timeOffset": 0.049759626388549805,
          "x": 117,
          "y": 170
        },
        {
          "timeOffset": 0.06637144088745117,
          "x": 117,
          "y": 174
        },
        {
          "timeOffset": 0.0830298662185669,
          "x": 118.5,
          "y": 183
        },
        {
          "timeOffset": 0.0996772050857544,
          "x": 118.5,
          "y": 186.8333282470703
        },
        {
          "timeOffset": 0.1163400411605835,
          "x": 118.5,
          "y": 191
        }
      ]
    },
    {
      "bounds": {
        "maxX": 134.5,
        "maxY": 196.5,
        "minX": 114,
        "minY": 169
      },
      "points": [
        {
          "timeOffset": 0,
          "x": 114,
          "y": 170
        },
        {
          "timeOffset": 0.06687557697296143,
          "x": 118,
          "y": 169
        },
        {
          "timeOffset": 0.09986269474029541,
          "x": 121.5,
          "y": 169
        },
        {
          "timeOffset": 0.1165311336517334,
          "x": 124.16666412353516,
          "y": 169
        },
        {
          "timeOffset": 0.13320469856262207,
          "x": 126.55810546875,
          "y": 169.23394775390625
        },
        {
          "timeOffset": 0.1498715877532959,
          "x": 126.58397674560547,
          "y": 172.77734375
        },
        {
          "timeOffset": 0.18318665027618408,
          "x": 124,
          "y": 176.5
        },
        {
          "timeOffset": 0.19985461235046387,
          "x": 121.83333587646484,
          "y": 178.3333282470703
        },
        {
          "timeOffset": 0.2165311574935913,
          "x": 120.11111450195312,
          "y": 179.61111450195312
        },
        {
          "timeOffset": 0.2331763505935669,
          "x": 118.5,
          "y": 180.5
        },
        {
          "timeOffset": 0.24982726573944092,
          "x": 120.5,
          "y": 180.5
        },
        {
          "timeOffset": 0.26653003692626953,
          "x": 123.41602325439453,
          "y": 180.77734375
        },
        {
          "timeOffset": 0.2831578254699707,
          "x": 127,
          "y": 181.5
        },
        {
          "timeOffset": 0.299845814704895,
          "x": 130.3000030517578,
          "y": 181.89999389648438
        },
        {
          "timeOffset": 0.316487193107605,
          "x": 134.5,
          "y": 183.5
        },
        {
          "timeOffset": 0.33314311504364014,
          "x": 134.5,
          "y": 186.6666717529297
        },
        {
          "timeOffset": 0.34982192516326904,
          "x": 134.5,
          "y": 190
        },
        {
          "timeOffset": 0.3664853572845459,
          "x": 132.52566528320312,
          "y": 193.34188842773438
        },
        {
          "timeOffset": 0.3831557035446167,
          "x": 128.5,
          "y": 196
        },
        {
          "timeOffset": 0.3998112678527832,
          "x": 123.49028778076172,
          "y": 196.40194702148438
        },
        {
          "timeOffset": 0.4164663553237915,
          "x": 120,
          "y": 196.5
        },
        {
          "timeOffset": 0.4331425428390503,
          "x": 115.99319458007812,
          "y": 194.4178009033203
        },
        {
          "timeOffset": 0.4498087167739868,
          "x": 114,
          "y": 191
        }
      ]
    },
    {
      "bounds": {
        "maxX": 141.5,
        "maxY": 182,
        "minX": 137,
        "minY": 164.5
      },
      "points": [
        {
          "timeOffset": 0,
          "x": 137,
          "y": 167.5
        },
        {
          "timeOffset": 0.01655125617980957,
          "x": 137,
          "y": 164.5
        },
        {
          "timeOffset": 0.04978621006011963,
          "x": 138.5,
          "y": 166
        },
        {
          "timeOffset": 0.06656122207641602,
          "x": 138.5,
          "y": 168.5
        },
        {
          "timeOffset": 0.0831596851348877,
          "x": 140,
          "y": 175.5
        },
        {
          "timeOffset": 0.09981441497802734,
          "x": 141.2427520751953,
          "y": 179.57125854492188
        },
        {
          "timeOffset": 0.11646556854248047,
          "x": 141.5,
          "y": 182
        }
      ]
    },
    {
      "bounds": {
        "maxX": 146,
        "maxY": 180,
        "minX": 144.5,
        "minY": 162.5
      },
      "points": [
        {
          "timeOffset": 0,
          "x": 144.5,
          "y": 162.5
        },
        {
          "timeOffset": 0.016521453857421875,
          "x": 144.5,
          "y": 164
        },
        {
          "timeOffset": 0.03311324119567871,
          "x": 144.5,
          "y": 165.5
        },
        {
          "timeOffset": 0.04976511001586914,
          "x": 144.5,
          "y": 169
        },
        {
          "timeOffset": 0.06641077995300293,
          "x": 146,
          "y": 173.5
        },
        {
          "timeOffset": 0.08308899402618408,
          "x": 146,
          "y": 177
        },
        {
          "timeOffset": 0.09975171089172363,
          "x": 146,
          "y": 180
        }
      ]
    },
    {
      "bounds": {
        "maxX": 153,
        "maxY": 173.5,
        "minX": 131.5,
        "minY": 168.5
      },
      "points": [
        {
          "timeOffset": 0,
          "x": 131.5,
          "y": 173.5
        },
        {
          "timeOffset": 0.049761176109313965,
          "x": 133,
          "y": 172.5
        },
        {
          "timeOffset": 0.0664360523223877,
          "x": 137,
          "y": 172
        },
        {
          "timeOffset": 0.08312666416168213,
          "x": 143,
          "y": 170.5
        },
        {
          "timeOffset": 0.09975779056549072,
          "x": 147.0527801513672,
          "y": 169.22360229492188
        },
        {
          "timeOffset": 0.11641716957092285,
          "x": 150,
          "y": 168.5
        },
        {
          "timeOffset": 0.13307428359985352,
          "x": 153,
          "y": 168.5
        }
      ]
    },
    {
      "bounds": {
        "maxX": 149,
        "maxY": 178.5,
        "minX": 134.5,
        "minY": 175.5
      },
      "points": [
        {
          "timeOffset": 0,
          "x": 137,
          "y": 178.5
        },
        {
          "timeOffset": 0.016507506370544434,
          "x": 134.5,
          "y": 178.5
        },
        {
          "timeOffset": 0.04975247383117676,
          "x": 136,
          "y": 178.5
        },
        {
          "timeOffset": 0.0664069652557373,
          "x": 138.5,
          "y": 177.5
        },
        {
          "timeOffset": 0.0830838680267334,
          "x": 144.5,
          "y": 177
        },
        {
          "timeOffset": 0.09976983070373535,
          "x": 149,
          "y": 175.5
        }
      ]
    },
    {
      "bounds": {
        "maxX": 172,
        "maxY": 185.5,
        "minX": 170.5,
        "minY": 170
      },
      "points": [
        {
          "timeOffset": 0,
          "x": 172,
          "y": 170
        },
        {
          "timeOffset": 0.04998588562011719,
          "x": 170.5,
          "y": 171
        },
        {
          "timeOffset": 0.0666041374206543,
          "x": 170.5,
          "y": 175
        },
        {
          "timeOffset": 0.08326756954193115,
          "x": 170.5,
          "y": 179.5
        },
        {
          "timeOffset": 0.09994471073150635,
          "x": 170.5,
          "y": 183.5
        },
        {
          "timeOffset": 0.11659908294677734,
          "x": 170.5,
          "y": 185.5
        }
      ]
    },
    {
      "bounds": {
        "maxX": 182,
        "maxY": 179,
        "minX": 164.5,
        "minY": 174
      },
      "points": [
        {
          "timeOffset": 0,
          "x": 164.5,
          "y": 179
        },
        {
          "timeOffset": 0.05860722064971924,
          "x": 166,
          "y": 178.5
        },
        {
          "timeOffset": 0.07527506351470947,
          "x": 170.5,
          "y": 178
        },
        {
          "timeOffset": 0.0919344425201416,
          "x": 175,
          "y": 177
        },
        {
          "timeOffset": 0.10864567756652832,
          "x": 178.6666717529297,
          "y": 175.8333282470703
        },
        {
          "timeOffset": 0.1252901554107666,
          "x": 182,
          "y": 174
        }
      ]
    }
  ]
}
