{
  "expectedClusterCount": 5,
  "expectedDisplayText": "B#\u25b313",
  "expectedTopGlyphs": [
    "B",
    "#",
    "\u25b3",
    "1",
    "3"
  ],
  "name": "BSharpMajor13",
  "strokes": [
    {
      "bounds": {
        "maxX": 118.5,
        "maxY": 195,
        "minX": 115.65811157226562,
        "minY": 169
      },
      "points": [
        {
          "timeOffset": 0,
          "x": 115.65811157226562,
          "y": 170.28062438964844
        },
        {
          "timeOffset": 0.06667757034301758,
          "x": 118.5,
          "y": 169
        },
        {
          "timeOffset": 0.10000991821289062,
          "x": 118.5,
          "y": 171
        },
        {
          "timeOffset": 0.15002954006195068,
          "x": 118.5,
          "y": 176.5
        },
        {
          "timeOffset": 0.1667172908782959,
          "x": 118.5,
          "y": 186.5
        },
        {
          "timeOffset": 0.18335413932800293,
          "x": 117.35355377197266,
          "y": 191.14645385742188
        },
        {
          "timeOffset": 0.1999976634979248,
          "x": 117,
          "y": 195
        }
      ]
    },
    {
      "bounds": {
        "maxX": 134.5,
        "maxY": 192,
        "minX": 111,
        "minY": 162.10845947265625
      },
      "points": [
        {
          "timeOffset": 0,
          "x": 111,
          "y": 165.5
        },
        {
          "timeOffset": 0.04995465278625488,
          "x": 114,
          "y": 165.5
        },
        {
          "timeOffset": 0.06662821769714355,
          "x": 120,
          "y": 164.5
        },
        {
          "timeOffset": 0.08330321311950684,
          "x": 127,
          "y": 162.5
        },
        {
          "timeOffset": 0.0999600887298584,
          "x": 131.01190185546875,
          "y": 162.10845947265625
        },
        {
          "timeOffset": 0.1166452169418335,
          "x": 130,
          "y": 164.5
        },
        {
          "timeOffset": 0.14995288848876953,
          "x": 125.5,
          "y": 169
        },
        {
          "timeOffset": 0.16662395000457764,
          "x": 121.83333587646484,
          "y": 172.1666717529297
        },
        {
          "timeOffset": 0.18329107761383057,
          "x": 118.5,
          "y": 175
        },
        {
          "timeOffset": 0.199945330619812,
          "x": 121.5,
          "y": 175.5
        },
        {
          "timeOffset": 0.24999535083770752,
          "x": 123.33333587646484,
          "y": 174.8333282470703
        },
        {
          "timeOffset": 0.26660799980163574,
          "x": 125.97087097167969,
          "y": 174.1681671142578
        },
        {
          "timeOffset": 0.2833366394042969,
          "x": 130,
          "y": 174
        },
        {
          "timeOffset": 0.2999683618545532,
          "x": 131.91603088378906,
          "y": 176.77734375
        },
        {
          "timeOffset": 0.31661415100097656,
          "x": 134.5,
          "y": 180
        },
        {
          "timeOffset": 0.333321213722229,
          "x": 134.02566528320312,
          "y": 183.15811157226562
        },
        {
          "timeOffset": 0.3499939441680908,
          "x": 131.5,
          "y": 187
        },
        {
          "timeOffset": 0.36662352085113525,
          "x": 128.5,
          "y": 190
        },
        {
          "timeOffset": 0.3833045959472656,
          "x": 125.5,
          "y": 192
        },
        {
          "timeOffset": 0.3999800682067871,
          "x": 123.2236099243164,
          "y": 191.5527801513672
        }
      ]
    },
    {
      "bounds": {
        "maxX": 146,
        "maxY": 176.5,
        "minX": 144.5,
        "minY": 154
      },
      "points": [
        {
          "timeOffset": 0,
          "x": 144.5,
          "y": 154
        },
        {
          "timeOffset": 0.033347368240356445,
          "x": 144.5,
          "y": 155.5
        },
        {
          "timeOffset": 0.049996256828308105,
          "x": 144.5,
          "y": 161
        },
        {
          "timeOffset": 0.06665873527526855,
          "x": 144.5,
          "y": 167.5
        },
        {
          "timeOffset": 0.08334195613861084,
          "x": 144.91603088378906,
          "y": 172.22265625
        },
        {
          "timeOffset": 0.09999215602874756,
          "x": 146,
          "y": 176.5
        }
      ]
    },
    {
      "bounds": {
        "maxX": 151.5,
        "maxY": 172.5,
        "minX": 150,
        "minY": 152.5
      },
      "points": [
        {
          "timeOffset": 0,
          "x": 151.5,
          "y": 152.5
        },
        {
          "timeOffset": 0.01667308807373047,
          "x": 151.5,
          "y": 155.5
        },
        {
          "timeOffset": 0.03334784507751465,
          "x": 150,
          "y": 162.5
        },
        {
          "timeOffset": 0.05000507831573486,
          "x": 150,
          "y": 169
        },
        {
          "timeOffset": 0.06668925285339355,
          "x": 150.47433471679688,
          "y": 170.84188842773438
        },
        {
          "timeOffset": 0.08334946632385254,
          "x": 151.5,
          "y": 172.5
        }
      ]
    },
    {
      "bounds": {
        "maxX": 157.5,
        "maxY": 164.5,
        "minX": 138.5,
        "minY": 160.5
      },
      "points": [
        {
          "timeOffset": 0,
          "x": 140,
          "y": 164.5
        },
        {
          "timeOffset": 0.016540884971618652,
          "x": 138.5,
          "y": 162.5
        },
        {
          "timeOffset": 0.04984259605407715,
          "x": 141.5,
          "y": 162.5
        },
        {
          "timeOffset": 0.0665360689163208,
          "x": 146,
          "y": 161
        },
        {
          "timeOffset": 0.08321404457092285,
          "x": 150.1666717529297,
          "y": 160.6666717529297
        },
        {
          "timeOffset": 0.09985768795013428,
          "x": 154.5,
          "y": 160.5
        },
        {
          "timeOffset": 0.1165550947189331,
          "x": 157.5,
          "y": 160.5
        }
      ]
    },
    {
      "bounds": {
        "maxX": 154.5,
        "maxY": 167.5,
        "minX": 140,
        "minY": 164
      },
      "points": [
        {
          "timeOffset": 0,
          "x": 143,
          "y": 167.5
        },
        {
          "timeOffset": 0.0258866548538208,
          "x": 140,
          "y": 167.5
        },
        {
          "timeOffset": 0.059154391288757324,
          "x": 143,
          "y": 167.5
        },
        {
          "timeOffset": 0.07583808898925781,
          "x": 146,
          "y": 166
        },
        {
          "timeOffset": 0.09247183799743652,
          "x": 153,
          "y": 164
        },
        {
          "timeOffset": 0.10919475555419922,
          "x": 154.5,
          "y": 164
        }
      ]
    },
    {
      "bounds": {
        "maxX": 182,
        "maxY": 176.5,
        "minX": 172,
        "minY": 161
      },
      "points": [
        {
          "timeOffset": 0,
          "x": 173.5,
          "y": 162.5
        },
        {
          "timeOffset": 0.0166780948638916,
          "x": 173.5,
          "y": 165.5
        },
        {
          "timeOffset": 0.03336739540100098,
          "x": 172.41603088378906,
          "y": 168.77734375
        },
        {
          "timeOffset": 0.05003702640533447,
          "x": 172,
          "y": 172.5
        },
        {
          "timeOffset": 0.06673645973205566,
          "x": 172,
          "y": 174.6666717529297
        },
        {
          "timeOffset": 0.08338499069213867,
          "x": 172,
          "y": 176.5
        },
        {
          "timeOffset": 0.11670219898223877,
          "x": 173,
          "y": 173.5
        },
        {
          "timeOffset": 0.13333725929260254,
          "x": 173.5,
          "y": 170.5
        },
        {
          "timeOffset": 0.15001356601715088,
          "x": 174.5,
          "y": 167
        },
        {
          "timeOffset": 0.16671717166900635,
          "x": 175,
          "y": 163.5
        },
        {
          "timeOffset": 0.18338465690612793,
          "x": 175,
          "y": 161
        },
        {
          "timeOffset": 0.23336291313171387,
          "x": 175,
          "y": 162.5
        },
        {
          "timeOffset": 0.2500380277633667,
          "x": 175.39044189453125,
          "y": 164.81234741210938
        },
        {
          "timeOffset": 0.2666811943054199,
          "x": 177.5,
          "y": 168.5
        },
        {
          "timeOffset": 0.28336799144744873,
          "x": 179,
          "y": 170.5
        },
        {
          "timeOffset": 0.30000734329223633,
          "x": 180.5,
          "y": 172.1666717529297
        },
        {
          "timeOffset": 0.31667840480804443,
          "x": 182,
          "y": 174.1666717529297
        },
        {
          "timeOffset": 0.3500102758407593,
          "x": 179.33941650390625,
          "y": 175.12205505371094
        },
        {
          "timeOffset": 0.38334596157073975,
          "x": 177.5,
          "y": 175.5
        },
        {
          "timeOffset": 0.4000126123428345,
          "x": 175.3333282470703,
          "y": 175.5
        },
        {
          "timeOffset": 0.41668009757995605,
          "x": 173.61111450195312,
          "y": 175.3333282470703
        },
        {
          "timeOffset": 0.43334364891052246,
          "x": 172,
          "y": 174
        }
      ]
    },
    {
      "bounds": {
        "maxX": 195,
        "maxY": 173.5,
        "minX": 190.5,
        "minY": 159.5
      },
      "points": [
        {
          "timeOffset": 0,
          "x": 193.5,
          "y": 161
        },
        {
          "timeOffset": 0.03133893013000488,
          "x": 192,
          "y": 159.5
        },
        {
          "timeOffset": 0.04799330234527588,
          "x": 190.5,
          "y": 161
        },
        {
          "timeOffset": 0.06471025943756104,
          "x": 190.5,
          "y": 165.5
        },
        {
          "timeOffset": 0.08138465881347656,
          "x": 190.97433471679688,
          "y": 168.84188842773438
        },
        {
          "timeOffset": 0.09802210330963135,
          "x": 192,
          "y": 172
        },
        {
          "timeOffset": 0.11473727226257324,
          "x": 193.5,
          "y": 172.6666717529297
        },
        {
          "timeOffset": 0.1313643455505371,
          "x": 195,
          "y": 173.5
        }
      ]
    },
    {
      "bounds": {
        "maxX": 213.58203125,
        "maxY": 176.5,
        "minX": 201,
        "minY": 160.65811157226562
      },
      "points": [
        {
          "timeOffset": 0,
          "x": 201,
          "y": 162
        },
        {
          "timeOffset": 0.0666579008102417,
          "x": 202.8333282470703,
          "y": 162
        },
        {
          "timeOffset": 0.08331918716430664,
          "x": 205.45957946777344,
          "y": 161.80303955078125
        },
        {
          "timeOffset": 0.10000932216644287,
          "x": 209.5,
          "y": 161
        },
        {
          "timeOffset": 0.11664962768554688,
          "x": 211.47433471679688,
          "y": 160.65811157226562
        },
        {
          "timeOffset": 0.13339722156524658,
          "x": 213.58203125,
          "y": 160.77439880371094
        },
        {
          "timeOffset": 0.1500033140182495,
          "x": 213.50680541992188,
          "y": 163.5821990966797
        },
        {
          "timeOffset": 0.18331968784332275,
          "x": 211.49319458007812,
          "y": 165.4178009033203
        },
        {
          "timeOffset": 0.19998741149902344,
          "x": 211,
          "y": 167
        },
        {
          "timeOffset": 0.21666371822357178,
          "x": 209.638671875,
          "y": 169.07421875
        },
        {
          "timeOffset": 0.24996590614318848,
          "x": 211,
          "y": 171
        },
        {
          "timeOffset": 0.30000030994415283,
          "x": 212.08396911621094,
          "y": 172.27734375
        },
        {
          "timeOffset": 0.31664228439331055,
          "x": 212.03216552734375,
          "y": 173.82354736328125
        },
        {
          "timeOffset": 0.333349347114563,
          "x": 210.84405517578125,
          "y": 175.10784912109375
        },
        {
          "timeOffset": 0.35001254081726074,
          "x": 209.5,
          "y": 176.5
        }
      ]
    }
  ]
}
