{
  "expectedClusterCount": 3,
  "expectedDisplayText": "G#6",
  "expectedTopGlyphs": [
    "G",
    "#",
    "6"
  ],
  "name": "GSharp6Captured03",
  "strokes": [
    {
      "bounds": {
        "maxX": 143,
        "maxY": 194.86264038085938,
        "minX": 118.5,
        "minY": 159.5
      },
      "points": [
        {
          "timeOffset": 0,
          "x": 131.5,
          "y": 159.5
        },
        {
          "timeOffset": 0.01664745807647705,
          "x": 129.6999969482422,
          "y": 161.39999389648438
        },
        {
          "timeOffset": 0.033322930335998535,
          "x": 127,
          "y": 164.5
        },
        {
          "timeOffset": 0.049996376037597656,
          "x": 124.16666412353516,
          "y": 169.1666717529297
        },
        {
          "timeOffset": 0.06666040420532227,
          "x": 121.5,
          "y": 174
        },
        {
          "timeOffset": 0.0833125114440918,
          "x": 120,
          "y": 180
        },
        {
          "timeOffset": 0.09998977184295654,
          "x": 118.9743423461914,
          "y": 184.84188842773438
        },
        {
          "timeOffset": 0.11667180061340332,
          "x": 118.5,
          "y": 189.5
        },
        {
          "timeOffset": 0.13335752487182617,
          "x": 121.19999694824219,
          "y": 192.60000610351562
        },
        {
          "timeOffset": 0.14998090267181396,
          "x": 123,
          "y": 194.5
        },
        {
          "timeOffset": 0.16666007041931152,
          "x": 125.98075866699219,
          "y": 194.86264038085938
        },
        {
          "timeOffset": 0.18335950374603271,
          "x": 131.5,
          "y": 194.5
        },
        {
          "timeOffset": 0.20002031326293945,
          "x": 137,
          "y": 192
        },
        {
          "timeOffset": 0.21668660640716553,
          "x": 140,
          "y": 189.5
        },
        {
          "timeOffset": 0.2333216667175293,
          "x": 143,
          "y": 187
        },
        {
          "timeOffset": 0.25002026557922363,
          "x": 143,
          "y": 184.5
        },
        {
          "timeOffset": 0.26663267612457275,
          "x": 142.50680541992188,
          "y": 182.0821990966797
        },
        {
          "timeOffset": 0.2833176851272583,
          "x": 140,
          "y": 180
        },
        {
          "timeOffset": 0.29998838901519775,
          "x": 136.5357666015625,
          "y": 179.18569946289062
        },
        {
          "timeOffset": 0.31666100025177,
          "x": 131.5,
          "y": 179
        },
        {
          "timeOffset": 0.33332359790802,
          "x": 129.58396911621094,
          "y": 179.27734375
        },
        {
          "timeOffset": 0.3499802350997925,
          "x": 127.49578857421875,
          "y": 180.5647735595703
        },
        {
          "timeOffset": 0.3833366632461548,
          "x": 130,
          "y": 181.5
        },
        {
          "timeOffset": 0.4000270366668701,
          "x": 134.34188842773438,
          "y": 181.02566528320312
        },
        {
          "timeOffset": 0.41665327548980713,
          "x": 138.5,
          "y": 180
        },
        {
          "timeOffset": 0.43332135677337646,
          "x": 141.02566528320312,
          "y": 178.34188842773438
        },
        {
          "timeOffset": 0.45003271102905273,
          "x": 143,
          "y": 176.5
        }
      ]
    },
    {
      "bounds": {
        "maxX": 153,
        "maxY": 172.5,
        "minX": 150,
        "minY": 158
      },
      "points": [
        {
          "timeOffset": 0,
          "x": 150,
          "y": 158
        },
        {
          "timeOffset": 0.03319382667541504,
          "x": 150,
          "y": 159.5
        },
        {
          "timeOffset": 0.08312392234802246,
          "x": 150,
          "y": 164
        },
        {
          "timeOffset": 0.09979605674743652,
          "x": 150,
          "y": 168.5
        },
        {
          "timeOffset": 0.11649549007415771,
          "x": 151.5,
          "y": 170.6666717529297
        },
        {
          "timeOffset": 0.13312828540802002,
          "x": 153,
          "y": 172.5
        }
      ]
    },
    {
      "bounds": {
        "maxX": 162,
        "maxY": 172,
        "minX": 159,
        "minY": 154.5
      },
      "points": [
        {
          "timeOffset": 0,
          "x": 159,
          "y": 154.5
        },
        {
          "timeOffset": 0.0498807430267334,
          "x": 159,
          "y": 158
        },
        {
          "timeOffset": 0.06655323505401611,
          "x": 159,
          "y": 164
        },
        {
          "timeOffset": 0.08322131633758545,
          "x": 159.41603088378906,
          "y": 168.72265625
        },
        {
          "timeOffset": 0.09985601902008057,
          "x": 162,
          "y": 172
        }
      ]
    },
    {
      "bounds": {
        "maxX": 164.5,
        "maxY": 165.5,
        "minX": 146,
        "minY": 161
      },
      "points": [
        {
          "timeOffset": 0,
          "x": 146,
          "y": 165.5
        },
        {
          "timeOffset": 0.05001962184906006,
          "x": 150,
          "y": 164
        },
        {
          "timeOffset": 0.0833202600479126,
          "x": 154.5,
          "y": 163.1666717529297
        },
        {
          "timeOffset": 0.099922776222229,
          "x": 159,
          "y": 162
        },
        {
          "timeOffset": 0.116660475730896,
          "x": 164.5,
          "y": 161
        }
      ]
    },
    {
      "bounds": {
        "maxX": 162,
        "maxY": 170.5,
        "minX": 146,
        "minY": 168.5
      },
      "points": [
        {
          "timeOffset": 0,
          "x": 150,
          "y": 169
        },
        {
          "timeOffset": 0.016614079475402832,
          "x": 147.5,
          "y": 170.5
        },
        {
          "timeOffset": 0.049948811531066895,
          "x": 146,
          "y": 170.5
        },
        {
          "timeOffset": 0.06656050682067871,
          "x": 147.5,
          "y": 170.5
        },
        {
          "timeOffset": 0.08330297470092773,
          "x": 150.48507690429688,
          "y": 170.3787384033203
        },
        {
          "timeOffset": 0.09990692138671875,
          "x": 154.5,
          "y": 170
        },
        {
          "timeOffset": 0.1165933609008789,
          "x": 158.52566528320312,
          "y": 169.15811157226562
        },
        {
          "timeOffset": 0.13325369358062744,
          "x": 162,
          "y": 168.5
        }
      ]
    },
    {
      "bounds": {
        "maxX": 195,
        "maxY": 171,
        "minX": 179,
        "minY": 153
      },
      "points": [
        {
          "timeOffset": 0,
          "x": 179,
          "y": 153
        },
        {
          "timeOffset": 0.0165860652923584,
          "x": 179,
          "y": 155.8333282470703
        },
        {
          "timeOffset": 0.03324532508850098,
          "x": 179,
          "y": 159
        },
        {
          "timeOffset": 0.04993641376495361,
          "x": 179.49319458007812,
          "y": 163.4178009033203
        },
        {
          "timeOffset": 0.06659054756164551,
          "x": 182,
          "y": 167.5
        },
        {
          "timeOffset": 0.08326244354248047,
          "x": 183.7572479248047,
          "y": 170.07125854492188
        },
        {
          "timeOffset": 0.09992361068725586,
          "x": 186.5,
          "y": 171
        },
        {
          "timeOffset": 0.11659383773803711,
          "x": 189.3333282470703,
          "y": 170.8333282470703
        },
        {
          "timeOffset": 0.133270263671875,
          "x": 191.71327209472656,
          "y": 170.0903778076172
        },
        {
          "timeOffset": 0.14991533756256104,
          "x": 193.5,
          "y": 168.5
        },
        {
          "timeOffset": 0.1665867567062378,
          "x": 194.5,
          "y": 165.5
        },
        {
          "timeOffset": 0.18324875831604004,
          "x": 195,
          "y": 162.5
        },
        {
          "timeOffset": 0.19991862773895264,
          "x": 194.6746063232422,
          "y": 160.87962341308594
        },
        {
          "timeOffset": 0.23324143886566162,
          "x": 192,
          "y": 162
        },
        {
          "timeOffset": 0.24991858005523682,
          "x": 189.3333282470703,
          "y": 164.6666717529297
        },
        {
          "timeOffset": 0.26659512519836426,
          "x": 186.5,
          "y": 167.5
        }
      ]
    }
  ]
}
