{
  "expectedClusterCount": 3,
  "expectedDisplayText": "G#9",
  "expectedTopGlyphs": [
    "G",
    "#",
    "9"
  ],
  "name": "GSharp9Captured03",
  "strokes": [
    {
      "bounds": {
        "maxX": 134.5,
        "maxY": 187,
        "minX": 118.5,
        "minY": 157.5
      },
      "points": [
        {
          "timeOffset": 0,
          "x": 134.5,
          "y": 157.5
        },
        {
          "timeOffset": 0.016726016998291016,
          "x": 133,
          "y": 157.5
        },
        {
          "timeOffset": 0.03341174125671387,
          "x": 131.14645385742188,
          "y": 157.85354614257812
        },
        {
          "timeOffset": 0.05002427101135254,
          "x": 128.44757080078125,
          "y": 159.4972381591797
        },
        {
          "timeOffset": 0.06666350364685059,
          "x": 125.5,
          "y": 163.5
        },
        {
          "timeOffset": 0.08332526683807373,
          "x": 121.5,
          "y": 168.5
        },
        {
          "timeOffset": 0.09999918937683105,
          "x": 118.5,
          "y": 174
        },
        {
          "timeOffset": 0.11665642261505127,
          "x": 118.5,
          "y": 178.8333282470703
        },
        {
          "timeOffset": 0.13331151008605957,
          "x": 118.5,
          "y": 183.5
        },
        {
          "timeOffset": 0.14998841285705566,
          "x": 121.24275207519531,
          "y": 186.07125854492188
        },
        {
          "timeOffset": 0.16664588451385498,
          "x": 123.46195983886719,
          "y": 186.80870056152344
        },
        {
          "timeOffset": 0.18333196640014648,
          "x": 127,
          "y": 187
        },
        {
          "timeOffset": 0.19999980926513672,
          "x": 129.6999969482422,
          "y": 186.60000610351562
        },
        {
          "timeOffset": 0.21664774417877197,
          "x": 131.8253936767578,
          "y": 184.62037658691406
        },
        {
          "timeOffset": 0.2333202362060547,
          "x": 134.5,
          "y": 182
        },
        {
          "timeOffset": 0.24998295307159424,
          "x": 134.5,
          "y": 179
        },
        {
          "timeOffset": 0.26662933826446533,
          "x": 134.5,
          "y": 176.8333282470703
        },
        {
          "timeOffset": 0.28335869312286377,
          "x": 134.5,
          "y": 175
        },
        {
          "timeOffset": 0.3000270128250122,
          "x": 130.5,
          "y": 175
        },
        {
          "timeOffset": 0.3167073726654053,
          "x": 127,
          "y": 175
        },
        {
          "timeOffset": 0.3335411548614502,
          "x": 124.5,
          "y": 175
        },
        {
          "timeOffset": 0.3500422239303589,
          "x": 123,
          "y": 175
        },
        {
          "timeOffset": 0.3999987840652466,
          "x": 127.16666412353516,
          "y": 175
        },
        {
          "timeOffset": 0.41669023036956787,
          "x": 131.5,
          "y": 175
        },
        {
          "timeOffset": 0.4334360361099243,
          "x": 134.5,
          "y": 174
        }
      ]
    },
    {
      "bounds": {
        "maxX": 146,
        "maxY": 165.5,
        "minX": 144.5,
        "minY": 154.5
      },
      "points": [
        {
          "timeOffset": 0,
          "x": 144.5,
          "y": 156
        },
        {
          "timeOffset": 0.016605138778686523,
          "x": 144.5,
          "y": 154.5
        },
        {
          "timeOffset": 0.04994487762451172,
          "x": 144.5,
          "y": 157
        },
        {
          "timeOffset": 0.06659698486328125,
          "x": 144.5,
          "y": 161
        },
        {
          "timeOffset": 0.08319270610809326,
          "x": 146,
          "y": 165.5
        }
      ]
    },
    {
      "bounds": {
        "maxX": 150,
        "maxY": 169,
        "minX": 149,
        "minY": 151.5
      },
      "points": [
        {
          "timeOffset": 0,
          "x": 150,
          "y": 154
        },
        {
          "timeOffset": 0.016543030738830566,
          "x": 149,
          "y": 151.5
        },
        {
          "timeOffset": 0.04982733726501465,
          "x": 149,
          "y": 155.5
        },
        {
          "timeOffset": 0.06649339199066162,
          "x": 150,
          "y": 161
        },
        {
          "timeOffset": 0.08316516876220703,
          "x": 150,
          "y": 165.5
        },
        {
          "timeOffset": 0.09983634948730469,
          "x": 150,
          "y": 169
        }
      ]
    },
    {
      "bounds": {
        "maxX": 153,
        "maxY": 159.5,
        "minX": 140,
        "minY": 157.5
      },
      "points": [
        {
          "timeOffset": 0,
          "x": 143,
          "y": 159.5
        },
        {
          "timeOffset": 0.016563057899475098,
          "x": 141.5,
          "y": 159.5
        },
        {
          "timeOffset": 0.033158302307128906,
          "x": 140,
          "y": 159.5
        },
        {
          "timeOffset": 0.06655991077423096,
          "x": 143,
          "y": 159
        },
        {
          "timeOffset": 0.08318078517913818,
          "x": 146,
          "y": 158.3333282470703
        },
        {
          "timeOffset": 0.0998389720916748,
          "x": 149,
          "y": 158
        },
        {
          "timeOffset": 0.11658453941345215,
          "x": 150.48507690429688,
          "y": 157.6212615966797
        },
        {
          "timeOffset": 0.13316619396209717,
          "x": 153,
          "y": 157.5
        }
      ]
    },
    {
      "bounds": {
        "maxX": 147.5,
        "maxY": 162.5,
        "minX": 143,
        "minY": 162
      },
      "points": [
        {
          "timeOffset": 0,
          "x": 146,
          "y": 162.5
        },
        {
          "timeOffset": 0.03334188461303711,
          "x": 144.5,
          "y": 162
        },
        {
          "timeOffset": 0.0499957799911499,
          "x": 143,
          "y": 162
        },
        {
          "timeOffset": 0.06669759750366211,
          "x": 144.5,
          "y": 162
        },
        {
          "timeOffset": 0.08331120014190674,
          "x": 146,
          "y": 162
        },
        {
          "timeOffset": 0.09995746612548828,
          "x": 147.5,
          "y": 162
        }
      ]
    },
    {
      "bounds": {
        "maxX": 175,
        "maxY": 168.5,
        "minX": 169,
        "minY": 155.6666717529297
      },
      "points": [
        {
          "timeOffset": 0,
          "x": 175,
          "y": 156
        },
        {
          "timeOffset": 0.03330278396606445,
          "x": 173.5,
          "y": 155.6666717529297
        },
        {
          "timeOffset": 0.04999828338623047,
          "x": 172,
          "y": 155.72222900390625
        },
        {
          "timeOffset": 0.0666583776473999,
          "x": 170.5,
          "y": 156.5
        },
        {
          "timeOffset": 0.08331692218780518,
          "x": 169,
          "y": 159
        },
        {
          "timeOffset": 0.09998631477355957,
          "x": 169,
          "y": 161.1666717529297
        },
        {
          "timeOffset": 0.11664462089538574,
          "x": 169.2703857421875,
          "y": 163.07940673828125
        },
        {
          "timeOffset": 0.1333218812942505,
          "x": 170.9472198486328,
          "y": 161.77639770507812
        },
        {
          "timeOffset": 0.16665303707122803,
          "x": 173.0527801513672,
          "y": 159.22360229492188
        },
        {
          "timeOffset": 0.18329060077667236,
          "x": 173.5,
          "y": 157.5
        },
        {
          "timeOffset": 0.21663367748260498,
          "x": 173.5,
          "y": 160
        },
        {
          "timeOffset": 0.2333083152770996,
          "x": 173.5,
          "y": 164
        },
        {
          "timeOffset": 0.250008225440979,
          "x": 173.5,
          "y": 166.1666717529297
        },
        {
          "timeOffset": 0.26665329933166504,
          "x": 173.5,
          "y": 168.5
        }
      ]
    }
  ]
}
