{
  "expectedClusterCount": 2,
  "expectedDisplayText": "C7",
  "expectedTopGlyphs": [
    "C",
    "7"
  ],
  "name": "C7Captured02",
  "strokes": [
    {
      "bounds": {
        "maxX": 138.5,
        "maxY": 189.5,
        "minX": 123,
        "minY": 167
      },
      "points": [
        {
          "timeOffset": 0,
          "x": 125.5,
          "y": 167
        },
        {
          "timeOffset": 0.016693592071533203,
          "x": 123,
          "y": 174
        },
        {
          "timeOffset": 0.03333425521850586,
          "x": 123,
          "y": 181.5
        },
        {
          "timeOffset": 0.049990177154541016,
          "x": 123,
          "y": 188
        },
        {
          "timeOffset": 0.06665241718292236,
          "x": 127,
          "y": 189.5
        },
        {
          "timeOffset": 0.08331418037414551,
          "x": 133,
          "y": 188
        },
        {
          "timeOffset": 0.09997403621673584,
          "x": 136.60955810546875,
          "y": 184.81234741210938
        },
        {
          "timeOffset": 0.11675870418548584,
          "x": 138.5,
          "y": 183
        }
      ]
    },
    {
      "bounds": {
        "maxX": 163.5,
        "maxY": 174,
        "minX": 150,
        "minY": 155.5
      },
      "points": [
        {
          "timeOffset": 0,
          "x": 150,
          "y": 158
        },
        {
          "timeOffset": 0.016464948654174805,
          "x": 151.5,
          "y": 157.5
        },
        {
          "timeOffset": 0.0663679838180542,
          "x": 154.5,
          "y": 157.5
        },
        {
          "timeOffset": 0.083030104637146,
          "x": 159,
          "y": 157.5
        },
        {
          "timeOffset": 0.09973227977752686,
          "x": 161.58396911621094,
          "y": 156.27734375
        },
        {
          "timeOffset": 0.11639726161956787,
          "x": 163.5,
          "y": 155.5
        },
        {
          "timeOffset": 0.14969944953918457,
          "x": 160.5,
          "y": 161
        },
        {
          "timeOffset": 0.16636621952056885,
          "x": 158.6999969482422,
          "y": 165.89999389648438
        },
        {
          "timeOffset": 0.18306338787078857,
          "x": 156,
          "y": 172
        },
        {
          "timeOffset": 0.19970262050628662,
          "x": 154.5,
          "y": 174
        }
      ]
    }
  ]
}
