{
  "expectedClusterCount": 3,
  "expectedDisplayText": "Db+",
  "expectedTopGlyphs": [
    "D",
    "b",
    "+"
  ],
  "name": "DFlatAugmentedCaptured01",
  "strokes": [
    {
      "bounds": {
        "maxX": 123,
        "maxY": 196.5,
        "minX": 120,
        "minY": 169
      },
      "points": [
        {
          "timeOffset": 0,
          "x": 120,
          "y": 169
        },
        {
          "timeOffset": 0.03314781188964844,
          "x": 121.5,
          "y": 172.5
        },
        {
          "timeOffset": 0.049791574478149414,
          "x": 123,
          "y": 177.5
        },
        {
          "timeOffset": 0.06642365455627441,
          "x": 123,
          "y": 188
        },
        {
          "timeOffset": 0.08314621448516846,
          "x": 123,
          "y": 192.5
        },
        {
          "timeOffset": 0.09975290298461914,
          "x": 123,
          "y": 195
        },
        {
          "timeOffset": 0.11642789840698242,
          "x": 123,
          "y": 196.5
        }
      ]
    },
    {
      "bounds": {
        "maxX": 139.5,
        "maxY": 196.5,
        "minX": 118.5,
        "minY": 165.5
      },
      "points": [
        {
          "timeOffset": 0,
          "x": 118.5,
          "y": 167.5
        },
        {
          "timeOffset": 0.016634821891784668,
          "x": 120,
          "y": 166
        },
        {
          "timeOffset": 0.033266663551330566,
          "x": 121.5,
          "y": 165.5
        },
        {
          "timeOffset": 0.04992413520812988,
          "x": 125.5,
          "y": 165.5
        },
        {
          "timeOffset": 0.06659162044525146,
          "x": 128.91603088378906,
          "y": 166.27734375
        },
        {
          "timeOffset": 0.08324635028839111,
          "x": 134.5,
          "y": 168.5
        },
        {
          "timeOffset": 0.0999077558517456,
          "x": 138,
          "y": 172.5
        },
        {
          "timeOffset": 0.11656677722930908,
          "x": 138.5,
          "y": 176.5
        },
        {
          "timeOffset": 0.13322043418884277,
          "x": 139.5,
          "y": 181.5
        },
        {
          "timeOffset": 0.14989614486694336,
          "x": 138.5,
          "y": 186.5
        },
        {
          "timeOffset": 0.16656172275543213,
          "x": 136.6666717529297,
          "y": 190.6666717529297
        },
        {
          "timeOffset": 0.18325304985046387,
          "x": 134.5,
          "y": 194.5
        },
        {
          "timeOffset": 0.1999272108078003,
          "x": 130,
          "y": 195.6666717529297
        },
        {
          "timeOffset": 0.21658027172088623,
          "x": 125.5,
          "y": 196.5
        },
        {
          "timeOffset": 0.23324096202850342,
          "x": 122.68765258789062,
          "y": 194.10955810546875
        },
        {
          "timeOffset": 0.24992942810058594,
          "x": 118.5,
          "y": 190
        },
        {
          "timeOffset": 0.2666240930557251,
          "x": 118.5,
          "y": 188
        }
      ]
    },
    {
      "bounds": {
        "maxX": 154.5,
        "maxY": 174,
        "minX": 141.5,
        "minY": 151.5
      },
      "points": [
        {
          "timeOffset": 0,
          "x": 141.5,
          "y": 151.5
        },
        {
          "timeOffset": 0.04987454414367676,
          "x": 143,
          "y": 154
        },
        {
          "timeOffset": 0.06652915477752686,
          "x": 144.5,
          "y": 157.5
        },
        {
          "timeOffset": 0.08318793773651123,
          "x": 146,
          "y": 162
        },
        {
          "timeOffset": 0.09987521171569824,
          "x": 146,
          "y": 166.6666717529297
        },
        {
          "timeOffset": 0.11654210090637207,
          "x": 146,
          "y": 171
        },
        {
          "timeOffset": 0.13320398330688477,
          "x": 146,
          "y": 174
        },
        {
          "timeOffset": 0.16652417182922363,
          "x": 146,
          "y": 172
        },
        {
          "timeOffset": 0.1832125186920166,
          "x": 146,
          "y": 169.5
        },
        {
          "timeOffset": 0.19989240169525146,
          "x": 146,
          "y": 166
        },
        {
          "timeOffset": 0.21652865409851074,
          "x": 147.8333282470703,
          "y": 163.8333282470703
        },
        {
          "timeOffset": 0.23318147659301758,
          "x": 150,
          "y": 162
        },
        {
          "timeOffset": 0.2665210962295532,
          "x": 152.64645385742188,
          "y": 162.85354614257812
        },
        {
          "timeOffset": 0.2831765413284302,
          "x": 154.04583740234375,
          "y": 164.70913696289062
        },
        {
          "timeOffset": 0.29985058307647705,
          "x": 154.5,
          "y": 167
        },
        {
          "timeOffset": 0.31651854515075684,
          "x": 154.02566528320312,
          "y": 168.84188842773438
        },
        {
          "timeOffset": 0.3331780433654785,
          "x": 152.5687255859375,
          "y": 170.2470245361328
        },
        {
          "timeOffset": 0.34983575344085693,
          "x": 150,
          "y": 171
        },
        {
          "timeOffset": 0.3665047883987427,
          "x": 147.47372436523438,
          "y": 170.0006866455078
        }
      ]
    },
    {
      "bounds": {
        "maxX": 177.5,
        "maxY": 187,
        "minX": 177.5,
        "minY": 169
      },
      "points": [
        {
          "timeOffset": 0,
          "x": 177.5,
          "y": 169
        },
        {
          "timeOffset": 0.06660091876983643,
          "x": 177.5,
          "y": 173.8333282470703
        },
        {
          "timeOffset": 0.08326125144958496,
          "x": 177.5,
          "y": 178.5
        },
        {
          "timeOffset": 0.09993588924407959,
          "x": 177.5,
          "y": 184.5
        },
        {
          "timeOffset": 0.11662948131561279,
          "x": 177.5,
          "y": 187
        }
      ]
    },
    {
      "bounds": {
        "maxX": 186.5,
        "maxY": 180.5,
        "minX": 170.5,
        "minY": 176.5
      },
      "points": [
        {
          "timeOffset": 0,
          "x": 172,
          "y": 180.5
        },
        {
          "timeOffset": 0.032961130142211914,
          "x": 170.5,
          "y": 179
        },
        {
          "timeOffset": 0.08287405967712402,
          "x": 175,
          "y": 179
        },
        {
          "timeOffset": 0.09962093830108643,
          "x": 178.6666717529297,
          "y": 178.6666717529297
        },
        {
          "timeOffset": 0.11620497703552246,
          "x": 182,
          "y": 178.5
        },
        {
          "timeOffset": 0.13290703296661377,
          "x": 183.91603088378906,
          "y": 177.27734375
        },
        {
          "timeOffset": 0.14954614639282227,
          "x": 186.5,
          "y": 176.5
        }
      ]
    }
  ]
}
