{
  "expectedClusterCount": 4,
  "expectedDisplayText": "Eb-7",
  "expectedTopGlyphs": [
    "E",
    "b",
    "-",
    "7"
  ],
  "name": "EFlatMinor7Captured02",
  "strokes": [
    {
      "bounds": {
        "maxX": 133,
        "maxY": 169,
        "minX": 118.5,
        "minY": 166
      },
      "points": [
        {
          "timeOffset": 0,
          "x": 118.5,
          "y": 169
        },
        {
          "timeOffset": 0.0665290355682373,
          "x": 121.5,
          "y": 168.5
        },
        {
          "timeOffset": 0.08317303657531738,
          "x": 126.66666412353516,
          "y": 167.1666717529297
        },
        {
          "timeOffset": 0.0999993085861206,
          "x": 131.5,
          "y": 166
        },
        {
          "timeOffset": 0.11656045913696289,
          "x": 133,
          "y": 166
        }
      ]
    },
    {
      "bounds": {
        "maxX": 128.5,
        "maxY": 199.5,
        "minX": 114,
        "minY": 167.5
      },
      "points": [
        {
          "timeOffset": 0,
          "x": 118.5,
          "y": 167.5
        },
        {
          "timeOffset": 0.033299922943115234,
          "x": 119.66326141357422,
          "y": 170.36959838867188
        },
        {
          "timeOffset": 0.06667113304138184,
          "x": 118.5,
          "y": 174
        },
        {
          "timeOffset": 0.08332419395446777,
          "x": 117,
          "y": 180.5
        },
        {
          "timeOffset": 0.09999513626098633,
          "x": 115.5,
          "y": 188
        },
        {
          "timeOffset": 0.11666655540466309,
          "x": 114,
          "y": 194.5
        },
        {
          "timeOffset": 0.13331007957458496,
          "x": 114.30000305175781,
          "y": 197.60000610351562
        },
        {
          "timeOffset": 0.14994966983795166,
          "x": 115.8438720703125,
          "y": 199.13702392578125
        },
        {
          "timeOffset": 0.16669166088104248,
          "x": 118.5,
          "y": 199.5
        },
        {
          "timeOffset": 0.18330919742584229,
          "x": 121.77735137939453,
          "y": 197.58396911621094
        },
        {
          "timeOffset": 0.1999441385269165,
          "x": 125.5,
          "y": 195
        },
        {
          "timeOffset": 0.21661388874053955,
          "x": 127,
          "y": 193.1666717529297
        },
        {
          "timeOffset": 0.23329699039459229,
          "x": 128.5,
          "y": 191.5
        }
      ]
    },
    {
      "bounds": {
        "maxX": 127,
        "maxY": 183.5,
        "minX": 115.5,
        "minY": 182
      },
      "points": [
        {
          "timeOffset": 0,
          "x": 115.5,
          "y": 183.5
        },
        {
          "timeOffset": 0.03321433067321777,
          "x": 115.5,
          "y": 182
        },
        {
          "timeOffset": 0.04982948303222656,
          "x": 118.5,
          "y": 182
        },
        {
          "timeOffset": 0.06648623943328857,
          "x": 121.5,
          "y": 182
        },
        {
          "timeOffset": 0.08315694332122803,
          "x": 125.03575897216797,
          "y": 182.81430053710938
        },
        {
          "timeOffset": 0.09985613822937012,
          "x": 127,
          "y": 183
        }
      ]
    },
    {
      "bounds": {
        "maxX": 150,
        "maxY": 178.5,
        "minX": 138.5,
        "minY": 160.5
      },
      "points": [
        {
          "timeOffset": 0,
          "x": 138.5,
          "y": 160.5
        },
        {
          "timeOffset": 0.049996256828308105,
          "x": 138.5,
          "y": 162.8333282470703
        },
        {
          "timeOffset": 0.06667780876159668,
          "x": 138.93707275390625,
          "y": 165.74282836914062
        },
        {
          "timeOffset": 0.08333003520965576,
          "x": 140,
          "y": 169
        },
        {
          "timeOffset": 0.09999370574951172,
          "x": 140,
          "y": 172.5
        },
        {
          "timeOffset": 0.11666715145111084,
          "x": 140,
          "y": 176.5
        },
        {
          "timeOffset": 0.13332617282867432,
          "x": 139.56292724609375,
          "y": 178.25717163085938
        },
        {
          "timeOffset": 0.16665005683898926,
          "x": 141.5,
          "y": 176.5
        },
        {
          "timeOffset": 0.19998502731323242,
          "x": 143.47433471679688,
          "y": 173.65811157226562
        },
        {
          "timeOffset": 0.2167905569076538,
          "x": 146,
          "y": 171
        },
        {
          "timeOffset": 0.23331165313720703,
          "x": 147.8333282470703,
          "y": 170.6666717529297
        },
        {
          "timeOffset": 0.2500026226043701,
          "x": 149.7176513671875,
          "y": 170.91265869140625
        },
        {
          "timeOffset": 0.26664435863494873,
          "x": 150,
          "y": 173.5
        },
        {
          "timeOffset": 0.28331971168518066,
          "x": 147.3333282470703,
          "y": 176.1666717529297
        },
        {
          "timeOffset": 0.30009543895721436,
          "x": 144.5,
          "y": 178.5
        },
        {
          "timeOffset": 0.3166705369949341,
          "x": 141.5,
          "y": 178.3333282470703
        },
        {
          "timeOffset": 0.33332395553588867,
          "x": 138.5,
          "y": 178
        }
      ]
    },
    {
      "bounds": {
        "maxX": 163.5,
        "maxY": 179,
        "minX": 159,
        "minY": 178.5
      },
      "points": [
        {
          "timeOffset": 0,
          "x": 159,
          "y": 178.5
        },
        {
          "timeOffset": 0.0663449764251709,
          "x": 161.5,
          "y": 179
        },
        {
          "timeOffset": 0.0996171236038208,
          "x": 163.5,
          "y": 179
        }
      ]
    },
    {
      "bounds": {
        "maxX": 179,
        "maxY": 169,
        "minX": 166,
        "minY": 157.5
      },
      "points": [
        {
          "timeOffset": 0,
          "x": 169,
          "y": 161
        },
        {
          "timeOffset": 0.03786873817443848,
          "x": 166,
          "y": 160.5
        },
        {
          "timeOffset": 0.0877755880355835,
          "x": 168.58396911621094,
          "y": 159.77734375
        },
        {
          "timeOffset": 0.10442888736724854,
          "x": 170.99815368652344,
          "y": 159.4570770263672
        },
        {
          "timeOffset": 0.12109756469726562,
          "x": 175,
          "y": 159
        },
        {
          "timeOffset": 0.13776373863220215,
          "x": 177.3214111328125,
          "y": 157.89523315429688
        },
        {
          "timeOffset": 0.17110896110534668,
          "x": 179,
          "y": 157.5
        },
        {
          "timeOffset": 0.20443522930145264,
          "x": 178,
          "y": 161
        },
        {
          "timeOffset": 0.22114014625549316,
          "x": 177.5,
          "y": 164.5
        },
        {
          "timeOffset": 0.23775064945220947,
          "x": 177.5,
          "y": 166.8333282470703
        },
        {
          "timeOffset": 0.2544252872467041,
          "x": 177.5,
          "y": 169
        },
        {
          "timeOffset": 0.3044055700302124,
          "x": 177.5,
          "y": 166.87037658691406
        },
        {
          "timeOffset": 0.35439932346343994,
          "x": 177.5,
          "y": 164.5
        }
      ]
    }
  ]
}
