{
  "expectedClusterCount": 4,
  "expectedDisplayText": "E#-7",
  "expectedTopGlyphs": [
    "E",
    "#",
    "-",
    "7"
  ],
  "name": "ESharpMinor7Captured03",
  "strokes": [
    {
      "bounds": {
        "maxX": 137,
        "maxY": 163.5,
        "minX": 115.5,
        "minY": 157.5
      },
      "points": [
        {
          "timeOffset": 0,
          "x": 115.5,
          "y": 163.5
        },
        {
          "timeOffset": 0.033084750175476074,
          "x": 118.5,
          "y": 162
        },
        {
          "timeOffset": 0.04973733425140381,
          "x": 125.5,
          "y": 160.5
        },
        {
          "timeOffset": 0.06640875339508057,
          "x": 131.5,
          "y": 158
        },
        {
          "timeOffset": 0.08305931091308594,
          "x": 137,
          "y": 157.5
        }
      ]
    },
    {
      "bounds": {
        "maxX": 134.5,
        "maxY": 193,
        "minX": 118.5,
        "minY": 165.5
      },
      "points": [
        {
          "timeOffset": 0,
          "x": 120,
          "y": 165.5
        },
        {
          "timeOffset": 0.016647934913635254,
          "x": 118.5,
          "y": 170.5
        },
        {
          "timeOffset": 0.0333099365234375,
          "x": 118.5,
          "y": 177
        },
        {
          "timeOffset": 0.049996376037597656,
          "x": 118.5,
          "y": 183.5
        },
        {
          "timeOffset": 0.06665658950805664,
          "x": 118.5,
          "y": 190.5
        },
        {
          "timeOffset": 0.09998941421508789,
          "x": 118.5,
          "y": 193
        },
        {
          "timeOffset": 0.11665761470794678,
          "x": 122.51493072509766,
          "y": 192.1212615966797
        },
        {
          "timeOffset": 0.13331198692321777,
          "x": 125.5,
          "y": 191.5
        },
        {
          "timeOffset": 0.1500617265701294,
          "x": 129.5,
          "y": 190
        },
        {
          "timeOffset": 0.1666315793991089,
          "x": 134.5,
          "y": 186.5
        }
      ]
    },
    {
      "bounds": {
        "maxX": 137,
        "maxY": 177,
        "minX": 121.5,
        "minY": 173.5
      },
      "points": [
        {
          "timeOffset": 0,
          "x": 121.5,
          "y": 177
        },
        {
          "timeOffset": 0.06657278537750244,
          "x": 128.5,
          "y": 176.5
        },
        {
          "timeOffset": 0.0832512378692627,
          "x": 134.5,
          "y": 175
        },
        {
          "timeOffset": 0.09985768795013428,
          "x": 137,
          "y": 173.5
        }
      ]
    },
    {
      "bounds": {
        "maxX": 153,
        "maxY": 175,
        "minX": 151.5,
        "minY": 158.5
      },
      "points": [
        {
          "timeOffset": 0,
          "x": 153,
          "y": 161
        },
        {
          "timeOffset": 0.03144180774688721,
          "x": 153,
          "y": 158.5
        },
        {
          "timeOffset": 0.09805762767791748,
          "x": 153,
          "y": 164
        },
        {
          "timeOffset": 0.11472952365875244,
          "x": 151.85354614257812,
          "y": 168.64645385742188
        },
        {
          "timeOffset": 0.131361722946167,
          "x": 151.5,
          "y": 172.5
        },
        {
          "timeOffset": 0.1480640172958374,
          "x": 153,
          "y": 175
        }
      ]
    },
    {
      "bounds": {
        "maxX": 162,
        "maxY": 171,
        "minX": 159,
        "minY": 157.5
      },
      "points": [
        {
          "timeOffset": 0,
          "x": 160.5,
          "y": 157.5
        },
        {
          "timeOffset": 0.047665953636169434,
          "x": 159,
          "y": 158
        },
        {
          "timeOffset": 0.06423509120941162,
          "x": 159,
          "y": 161
        },
        {
          "timeOffset": 0.0809396505355835,
          "x": 160.5,
          "y": 167
        },
        {
          "timeOffset": 0.09759318828582764,
          "x": 162,
          "y": 171
        }
      ]
    },
    {
      "bounds": {
        "maxX": 163.5,
        "maxY": 167.5,
        "minX": 149,
        "minY": 162.5
      },
      "points": [
        {
          "timeOffset": 0,
          "x": 151.5,
          "y": 167.5
        },
        {
          "timeOffset": 0.01648557186126709,
          "x": 149,
          "y": 167
        },
        {
          "timeOffset": 0.04982316493988037,
          "x": 150,
          "y": 164.5
        },
        {
          "timeOffset": 0.08307993412017822,
          "x": 156,
          "y": 163.5
        },
        {
          "timeOffset": 0.09972774982452393,
          "x": 159,
          "y": 163.1666717529297
        },
        {
          "timeOffset": 0.11642348766326904,
          "x": 162,
          "y": 162.5
        },
        {
          "timeOffset": 0.1330878734588623,
          "x": 163.5,
          "y": 162.5
        }
      ]
    },
    {
      "bounds": {
        "maxX": 166,
        "maxY": 172.5,
        "minX": 147.5,
        "minY": 168.5
      },
      "points": [
        {
          "timeOffset": 0,
          "x": 153,
          "y": 170.5
        },
        {
          "timeOffset": 0.02342545986175537,
          "x": 147.5,
          "y": 172.5
        },
        {
          "timeOffset": 0.07339179515838623,
          "x": 150.48507690429688,
          "y": 172.3787384033203
        },
        {
          "timeOffset": 0.09003889560699463,
          "x": 154.5,
          "y": 172
        },
        {
          "timeOffset": 0.10672712326049805,
          "x": 159,
          "y": 170.5
        },
        {
          "timeOffset": 0.12336814403533936,
          "x": 163.5,
          "y": 169
        },
        {
          "timeOffset": 0.1400541067123413,
          "x": 166,
          "y": 168.5
        }
      ]
    },
    {
      "bounds": {
        "maxX": 177.5,
        "maxY": 183.5,
        "minX": 170.5,
        "minY": 181.5
      },
      "points": [
        {
          "timeOffset": 0,
          "x": 170.5,
          "y": 183
        },
        {
          "timeOffset": 0.049776554107666016,
          "x": 172,
          "y": 183.5
        },
        {
          "timeOffset": 0.06633651256561279,
          "x": 175,
          "y": 183
        },
        {
          "timeOffset": 0.0830078125,
          "x": 177.5,
          "y": 181.5
        }
      ]
    },
    {
      "bounds": {
        "maxX": 195,
        "maxY": 181.5,
        "minX": 185,
        "minY": 161
      },
      "points": [
        {
          "timeOffset": 0,
          "x": 185,
          "y": 164
        },
        {
          "timeOffset": 0.06647741794586182,
          "x": 186.5,
          "y": 163.5
        },
        {
          "timeOffset": 0.08312761783599854,
          "x": 189.01492309570312,
          "y": 162.6212615966797
        },
        {
          "timeOffset": 0.09977996349334717,
          "x": 190.99609375,
          "y": 161.93768310546875
        },
        {
          "timeOffset": 0.11647665500640869,
          "x": 195,
          "y": 161
        },
        {
          "timeOffset": 0.1331174373626709,
          "x": 195,
          "y": 162.5
        },
        {
          "timeOffset": 0.14977669715881348,
          "x": 195,
          "y": 166
        },
        {
          "timeOffset": 0.1664656400680542,
          "x": 195,
          "y": 170
        },
        {
          "timeOffset": 0.18310177326202393,
          "x": 193.72360229492188,
          "y": 175.0527801513672
        },
        {
          "timeOffset": 0.19979751110076904,
          "x": 193.5,
          "y": 178
        },
        {
          "timeOffset": 0.21648335456848145,
          "x": 193.5,
          "y": 179.8333282470703
        },
        {
          "timeOffset": 0.23314809799194336,
          "x": 193.5,
          "y": 181.5
        }
      ]
    }
  ]
}
