{
  "expectedClusterCount": 3,
  "expectedDisplayText": "F#-",
  "expectedTopGlyphs": [
    "F",
    "#",
    "-"
  ],
  "name": "FSharpMinorCaptured03",
  "strokes": [
    {
      "bounds": {
        "maxX": 118.5,
        "maxY": 194,
        "minX": 117,
        "minY": 172.5
      },
      "points": [
        {
          "timeOffset": 0,
          "x": 117,
          "y": 172.5
        },
        {
          "timeOffset": 0.03310346603393555,
          "x": 117,
          "y": 174
        },
        {
          "timeOffset": 0.04968714714050293,
          "x": 117,
          "y": 176.5
        },
        {
          "timeOffset": 0.0663682222366333,
          "x": 117,
          "y": 182
        },
        {
          "timeOffset": 0.08301520347595215,
          "x": 117.35355377197266,
          "y": 187.35354614257812
        },
        {
          "timeOffset": 0.09968221187591553,
          "x": 118.5,
          "y": 194
        },
        {
          "timeOffset": 0.13298988342285156,
          "x": 118.5,
          "y": 192
        }
      ]
    },
    {
      "bounds": {
        "maxX": 130,
        "maxY": 172.5,
        "minX": 112.5,
        "minY": 167
      },
      "points": [
        {
          "timeOffset": 0,
          "x": 112.5,
          "y": 172.5
        },
        {
          "timeOffset": 0.016656160354614258,
          "x": 114,
          "y": 172.5
        },
        {
          "timeOffset": 0.03329789638519287,
          "x": 115.5,
          "y": 172.5
        },
        {
          "timeOffset": 0.04996514320373535,
          "x": 118.91602325439453,
          "y": 171.72265625
        },
        {
          "timeOffset": 0.06665277481079102,
          "x": 123,
          "y": 170.5
        },
        {
          "timeOffset": 0.08335435390472412,
          "x": 126.66666412353516,
          "y": 168.6666717529297
        },
        {
          "timeOffset": 0.09998965263366699,
          "x": 130,
          "y": 167
        }
      ]
    },
    {
      "bounds": {
        "maxX": 130,
        "maxY": 181.5,
        "minX": 115.5,
        "minY": 177.5
      },
      "points": [
        {
          "timeOffset": 0,
          "x": 118.5,
          "y": 181.5
        },
        {
          "timeOffset": 0.016475439071655273,
          "x": 117,
          "y": 181.5
        },
        {
          "timeOffset": 0.03309190273284912,
          "x": 115.5,
          "y": 181.5
        },
        {
          "timeOffset": 0.0497434139251709,
          "x": 117,
          "y": 181.5
        },
        {
          "timeOffset": 0.06640958786010742,
          "x": 121.5,
          "y": 181.5
        },
        {
          "timeOffset": 0.08313596248626709,
          "x": 123.48506927490234,
          "y": 180.3787384033203
        },
        {
          "timeOffset": 0.09975409507751465,
          "x": 128.5,
          "y": 178.5
        },
        {
          "timeOffset": 0.11658203601837158,
          "x": 130,
          "y": 177.5
        }
      ]
    },
    {
      "bounds": {
        "maxX": 138.5,
        "maxY": 180,
        "minX": 138.5,
        "minY": 159.5
      },
      "points": [
        {
          "timeOffset": 0,
          "x": 138.5,
          "y": 162
        },
        {
          "timeOffset": 0.016629576683044434,
          "x": 138.5,
          "y": 159.5
        },
        {
          "timeOffset": 0.04993295669555664,
          "x": 138.5,
          "y": 164
        },
        {
          "timeOffset": 0.06663095951080322,
          "x": 138.5,
          "y": 170.5
        },
        {
          "timeOffset": 0.08326935768127441,
          "x": 138.5,
          "y": 177.5
        },
        {
          "timeOffset": 0.09991312026977539,
          "x": 138.5,
          "y": 180
        }
      ]
    },
    {
      "bounds": {
        "maxX": 144.5,
        "maxY": 174,
        "minX": 143,
        "minY": 156
      },
      "points": [
        {
          "timeOffset": 0,
          "x": 144.5,
          "y": 157.5
        },
        {
          "timeOffset": 0.016628384590148926,
          "x": 143,
          "y": 156
        },
        {
          "timeOffset": 0.0332486629486084,
          "x": 143,
          "y": 161
        },
        {
          "timeOffset": 0.06658554077148438,
          "x": 143,
          "y": 167.5
        },
        {
          "timeOffset": 0.08325064182281494,
          "x": 143.2572479248047,
          "y": 171.57125854492188
        },
        {
          "timeOffset": 0.09994029998779297,
          "x": 144.5,
          "y": 174
        }
      ]
    },
    {
      "bounds": {
        "maxX": 147.5,
        "maxY": 168.5,
        "minX": 134.5,
        "minY": 164
      },
      "points": [
        {
          "timeOffset": 0,
          "x": 137,
          "y": 168.5
        },
        {
          "timeOffset": 0.01656365394592285,
          "x": 134.5,
          "y": 168.5
        },
        {
          "timeOffset": 0.03316617012023926,
          "x": 136,
          "y": 167
        },
        {
          "timeOffset": 0.06648027896881104,
          "x": 138.5,
          "y": 165.5
        },
        {
          "timeOffset": 0.0831679105758667,
          "x": 142.52566528320312,
          "y": 164.65811157226562
        },
        {
          "timeOffset": 0.09981083869934082,
          "x": 146,
          "y": 164
        },
        {
          "timeOffset": 0.11648762226104736,
          "x": 147.5,
          "y": 164
        }
      ]
    },
    {
      "bounds": {
        "maxX": 143,
        "maxY": 174,
        "minX": 134.5,
        "minY": 172.5
      },
      "points": [
        {
          "timeOffset": 0,
          "x": 138.5,
          "y": 172.5
        },
        {
          "timeOffset": 0.016608595848083496,
          "x": 134.5,
          "y": 174
        },
        {
          "timeOffset": 0.049956321716308594,
          "x": 138.5,
          "y": 174
        },
        {
          "timeOffset": 0.06665623188018799,
          "x": 143,
          "y": 173.5
        }
      ]
    },
    {
      "bounds": {
        "maxX": 162,
        "maxY": 187,
        "minX": 153,
        "minY": 184.5
      },
      "points": [
        {
          "timeOffset": 0,
          "x": 154.5,
          "y": 187
        },
        {
          "timeOffset": 0.03330230712890625,
          "x": 153,
          "y": 186.5
        },
        {
          "timeOffset": 0.04987287521362305,
          "x": 154.5,
          "y": 186.5
        },
        {
          "timeOffset": 0.06653761863708496,
          "x": 159,
          "y": 185
        },
        {
          "timeOffset": 0.08320343494415283,
          "x": 162,
          "y": 184.5
        }
      ]
    }
  ]
}
